codes/diff.sv
`timescale 1ns/100ps
module d_ff ( clk_80, rst_80, d_80, q_80 );
        parameter REG_SIZE = 4;
        input   clk_80, rst_80;
        input   [(REG_SIZE - 1) :0] d_80;
        output  [(REG_SIZE - 1) :0] q_80;

        wire    clk_80, rst_80;
        wire    [(REG_SIZE - 1) :0] d_80;
        reg     [(REG_SIZE - 1) :0] q_80;

        always @ ( posedge clk_80 or posedge rst_80 )
        begin
                if (rst_80)
                        q_80 <= 0;
                else
                        q_80 <= d_80;
        end
endmodule

codes/saturation.sv
`timescale 1ns/100ps
module saturation_logic ( sum_saturated_80, sum_80, carry_80, oflow_80 );
parameter       WIDTH_SUM = 4;
output  [ WIDTH_SUM - 1:0 ] sum_saturated_80;
input   [ WIDTH_SUM - 1:0 ] sum_80;
input   carry_80, oflow_80;

reg     [ WIDTH_SUM - 1:0 ] sum_saturated_80;
wire    [ WIDTH_SUM - 1:0 ] sum_80;
wire    carry_80, oflow_80;
        // **** Saturation logic ****
        // if there is no overflow, no saturation is necessary
        //              * check and correct for illegal number (1000)
        // if there is overflow, check for the carry out
        // * carry out = 0 => MSB of the sum = 1
        //   ( 2 +ve numbers were added & sum has become a -ve number )
        //   saturate sum to the highest positive number = 0111 (+7)
        // * carry out = 1 => MSB of the sum = 0
        //   ( 2 -ve numbers were added & sum has become a +ve number )
        //   saturate sum to the lowest negative number = 1001 (-7)
        always @ ( carry_80 or oflow_80 or sum_80 )
        begin
                case ( {carry_80,oflow_80} )
                2'b00 : begin
                                if ((sum_80[WIDTH_SUM-1]==1'b1) && (sum_80[WIDTH_SUM-2:0]==0))
                                        sum_saturated_80 = sum_80 + 1;
                                else
                                        sum_saturated_80 = sum_80;
                                end

                2'b10 : begin
                                if ((sum_80[WIDTH_SUM-1]==1'b1) && (sum_80[WIDTH_SUM-2:0]==0))
                                        sum_saturated_80 = sum_80 + 1;
                                else
                                        sum_saturated_80 = sum_80;
                                end

                2'b01 : sum_saturated_80 = { 1'b0, { (WIDTH_SUM-1) {1'b1} } };

                2'b11 : sum_saturated_80 = { 1'b1, { (WIDTH_SUM-2) {1'b0} }, 1'b1 };
                endcase
        end
endmodule

codes/add.sv
`timescale 1 ps / 1 ps
// synopsys translate_on
module add (
	dataa,
	datab,
	cout,
	overflow,
	result);

	input	[10:0]  dataa;
	input	[10:0]  datab;
	output	reg  cout;
	output	reg  overflow;
	output reg	[10:0]  result;

  
  always @(dataa or datab) begin
    {cout,result} = dataa + datab;
    
    if((dataa[10]==datab[10])&&(datab[10]==result[10])&&(dataa[10]==result[10]))
      overflow = 1;
    else  if((dataa[10]==datab[10])&&(datab[10]!=result[10])&&(dataa[10]!=result[10])) begin
      overflow = 0;
    end
    else begin
      overflow = 1;
    end
      
  end
      

endmodule

codes/rounding.sv
`timescale 1ns/100ps
module rounding_logic ( prod_rounded_80, prod_80 );

parameter WIDTH_PROD = 8;
parameter WIDTH_PROD_ROUNDED = 4;

input    [ WIDTH_PROD - 1:0 ]           prod_80;
output   [ WIDTH_PROD_ROUNDED - 1:0 ]   prod_rounded_80;

wire     [ WIDTH_PROD - 1:0 ]           prod_80;
reg      [ WIDTH_PROD_ROUNDED - 1:0 ]   prod_rounded_80;

// Truncation and Rounding logic
// -----------------------------
        // 1. throw away the MSB (redundant sign bit)
        // 2. check for the possibility of the illegal number
        //              * if the product is positive
        //         and if the to-be-rounded bits are 0111, and the next bit is 1,
        //                 don't add 1. Just truncate it to 0111
        //              * if the product is negative
        //            if the to-be-rounded bits are 1000, add 1 to make it 1001
        // 3. add rounding logic for both positive and negative products
        //              * If the next bit is 1, add 1 to the to-be-rounded bits
        //              * If the next bit is 0, just truncate
always @ (prod_80)
begin
        if ( prod_80[WIDTH_PROD-1] == 1'b0 )
        begin
                if ( & prod_80[(WIDTH_PROD-2-1):(WIDTH_PROD_ROUNDED-1)] )
                        prod_rounded_80 <=
                          prod_80[(WIDTH_PROD-2):(WIDTH_PROD-WIDTH_PROD_ROUNDED-1)];
                else
                begin
                   if ( prod_80[WIDTH_PROD-WIDTH_PROD_ROUNDED-2] == 1'b1 )
                      prod_rounded_80 <= prod_80[(WIDTH_PROD-2):(WIDTH_PROD-2-(WIDTH_PROD_ROUNDED-1))]+1;
                   else
                      prod_rounded_80 <= prod_80[(WIDTH_PROD-2):(WIDTH_PROD-2-(WIDTH_PROD_ROUNDED-1))];
                end
        end
        else
        begin
                if( prod_80[(WIDTH_PROD-2-1):(WIDTH_PROD-WIDTH_PROD_ROUNDED-1)] == 0 )
                   prod_rounded_80 <= prod_80[(WIDTH_PROD-2):(WIDTH_PROD-WIDTH_PROD_ROUNDED-1)]+1;
                else
                begin
                   if ( prod_80[WIDTH_PROD-WIDTH_PROD_ROUNDED-2] == 1'b1 )
                      prod_rounded_80 <= prod_80[(WIDTH_PROD-2):(WIDTH_PROD-2-(WIDTH_PROD_ROUNDED-1))]+1;
                   else
                      prod_rounded_80 <= prod_80[(WIDTH_PROD-2):(WIDTH_PROD-2-(WIDTH_PROD_ROUNDED-1))];
                end
        end
end

endmodule

codes/mult.sv

`timescale 1 ps / 1 ps
// synopsys translate_on
module mult (
	dataa,
	datab,
	result);

	input	[8:0]  dataa;
	input	[7:0]  datab;
	output wire	[16:0]  result;

	assign result = dataa*datab;


endmodule

codes/design.sv
`include "diff.sv"
`include "mult.sv"
`include "rounding.sv"
`include "saturation.sv"
`include "add.sv"

`timescale 1ns/100ps
module mat_mult (A00_80, A01_80, A02_80, A03_80, B00_80, B01_80, B02_80, B03_80, 
clk_80, rst_80, AB00_80);
        // Parameterizable with respect to bit widths
        // WIDTH_SUM is separately declared for the case in which A00_80 and B00_80 have
        // different widths, to specify the number of bits to which the product has to be
        // rounded

        parameter       WIDTH_A_80 = 9;
        parameter       WIDTH_B_80 = 8;
        parameter       WIDTH_PROD  = WIDTH_A_80 + WIDTH_B_80;
        parameter       WIDTH_PROD_ROUNDED   = 9;
        parameter       WIDTH_SUM   = 11;

        // Input ports
        input           clk_80, rst_80;
        input            [(WIDTH_A_80 - 1) : 0] A00_80, A01_80, A02_80, A03_80;
        input            [(WIDTH_B_80 - 1) : 0] B00_80, B01_80, B02_80, B03_80;

        // Output ports
        output           [(WIDTH_SUM - 1) : 0] AB00_80;

        wire    	       clk_80, rst_80;
        wire             [(WIDTH_A_80 - 1) : 0] A00_80, A01_80, A02_80, A03_80;
        wire             [(WIDTH_B_80 - 1) : 0] B00_80, B01_80, B02_80, B03_80;
        reg              [(WIDTH_A_80 - 1) :0] A00_80_corrected, A01_80_corrected, A02_80_corrected, A03_80_corrected;
        reg              [(WIDTH_B_80 - 1) :0] B00_80_corrected, B01_80_corrected, B02_80_corrected, B03_80_corrected;
        wire             [(WIDTH_PROD -1) : 0] product0_80, product1_80, product2_80, product3_80;
        wire             [(WIDTH_PROD_ROUNDED -1) : 0] product0_rounded_80, product1_rounded_80, product2_rounded_80, product3_rounded_80;
        wire             [(WIDTH_SUM-1) : 0] adder0_sum_80, adder1_sum_80, adder2_sum_80;
        wire             c_out0_80, c_out1_80, c_out2_80, o_flow0_80, o_flow1_80, o_flow2_80;
        wire             [(WIDTH_SUM-1) : 0] a0_in_80, a1_in_80, a2_in_80;
        wire             [(WIDTH_SUM - 1) : 0]   AB00_80;


        // Illegal Number Detection Logic
        // --------------------------------------------
        // In case of 4 bits, if data = -1 = 1000 (illegal in case of fractional numbers),
        // make it the least negative fractional number that can be represented by 4 bits.
        // Therefore, add 1 and make it 1001 = -0.875

        always @ (A00_80  or B00_80)
        begin

                if ((A00_80[WIDTH_A_80-1] == 1'b1) && (A00_80[WIDTH_A_80-2 : 0] == 0))
                        A00_80_corrected = A00_80 + 1;

                else
                        A00_80_corrected = A00_80;
                if ((B00_80[WIDTH_B_80-1] == 1'b1) && (B00_80[WIDTH_B_80-2 : 0] == 0))
                        B00_80_corrected = B00_80 + 1;

                else
                        B00_80_corrected = B00_80;
        end
		  
		  always @ (A01_80  or B01_80)
        begin

                if ((A01_80[WIDTH_A_80-1] == 1'b1) && (A01_80[WIDTH_A_80-2 : 0] == 0))
                        A01_80_corrected = A01_80 + 1;

                else
                        A01_80_corrected = A01_80;
                if ((B01_80[WIDTH_B_80-1] == 1'b1) && (B01_80[WIDTH_B_80-2 : 0] == 0))
                        B01_80_corrected = B01_80 + 1;

                else
                        B01_80_corrected = B01_80;
        end
		  
		  always @ (A02_80  or B02_80)
        begin

                if ((A02_80[WIDTH_A_80-1] == 1'b1) && (A02_80[WIDTH_A_80-2 : 0] == 0))
                        A02_80_corrected = A02_80 + 1;

                else
                        A02_80_corrected = A02_80;
                if ((B02_80[WIDTH_B_80-1] == 1'b1) && (B02_80[WIDTH_B_80-2 : 0] == 0))
                        B02_80_corrected = B02_80 + 1;

                else
                        B02_80_corrected = B02_80;
        end
		  
		  always @ (A03_80  or B03_80)
        begin

                if ((A03_80[WIDTH_A_80-1] == 1'b1) && (A03_80[WIDTH_A_80-2 : 0] == 0))
                        A03_80_corrected = A03_80 + 1;

                else
                        A03_80_corrected = A03_80;
                if ((B03_80[WIDTH_B_80-1] == 1'b1) && (B03_80[WIDTH_B_80-2 : 0] == 0))
                        B03_80_corrected = B03_80 + 1;

                else
                        B03_80_corrected = B03_80;
        end

        // MULTIPLIER
        // ==========
        // Instantiating LPM mult module

		  mult m0 (.dataa(A00_80_corrected),.datab(B00_80_corrected),.result(product0_80));
		  mult m1 (.dataa(A01_80_corrected),.datab(B01_80_corrected),.result(product1_80));
		  mult m2 (.dataa(A02_80_corrected),.datab(B02_80_corrected),.result(product2_80));
		  mult m3 (.dataa(A03_80_corrected),.datab(B03_80_corrected),.result(product3_80));
        /*defparam
                mult.WIDTH_A     = WIDTH_A_80,
                mult.WIDTH_B     = WIDTH_B_80,
                mult.WIDTH_PROD  = WIDTH_PROD;
			*/
        // Truncation and Rounding logic

        rounding_logic r0 ( product0_rounded_80, product0_80 );
        rounding_logic r1 ( product1_rounded_80, product1_80 );
        rounding_logic r2 ( product2_rounded_80, product2_80 );
        rounding_logic r3 ( product3_rounded_80, product3_80 );
        defparam
                r0.WIDTH_PROD         = WIDTH_PROD,
                r0.WIDTH_PROD_ROUNDED = WIDTH_PROD_ROUNDED;
        defparam
                r1.WIDTH_PROD         = WIDTH_PROD,
                r1.WIDTH_PROD_ROUNDED = WIDTH_PROD_ROUNDED;
        defparam
                r2.WIDTH_PROD         = WIDTH_PROD,
                r2.WIDTH_PROD_ROUNDED = WIDTH_PROD_ROUNDED;
        defparam
                r3.WIDTH_PROD         = WIDTH_PROD,
                r3.WIDTH_PROD_ROUNDED = WIDTH_PROD_ROUNDED;

        // Adder
        // --------
        // Instantiating an adder module
        // This adder has carry out and overflow bits for calculations in the saturation logic

        add a0 ( .dataa({{(WIDTH_SUM - WIDTH_PROD_ROUNDED){product0_rounded_80[WIDTH_PROD_ROUNDED-1]}},{product0_rounded_80}}), .datab({{(WIDTH_SUM - WIDTH_PROD_ROUNDED){product1_rounded_80[WIDTH_PROD_ROUNDED-1]}},{product1_rounded_80}}), .result(adder0_sum_80), .cout(c_out0_80),.overflow(o_flow0_80) );
        add a1 ( .dataa({{(WIDTH_SUM - WIDTH_PROD_ROUNDED){product2_rounded_80[WIDTH_PROD_ROUNDED-1]}},{product2_rounded_80}}), .datab({{(WIDTH_SUM - WIDTH_PROD_ROUNDED){product3_rounded_80[WIDTH_PROD_ROUNDED-1]}},{product3_rounded_80}}), .result(adder1_sum_80), .cout(c_out1_80),.overflow(o_flow1_80) );
        add a2 ( .dataa(a0_in_80), .datab(a1_in_80), .result(adder2_sum_80), .cout(c_out2_80),.overflow(o_flow2_80) );
		  
        // Saturation logic
        saturation_logic sat_sum0 ( a0_in_80, adder0_sum_80, c_out0_80, o_flow0_80 );
        saturation_logic sat_sum1 ( a1_in_80, adder1_sum_80, c_out1_80, o_flow1_80 );
        saturation_logic sat_sum2 ( a2_in_80, adder2_sum_80, c_out2_80, o_flow2_80 );

        defparam
                sat_sum0.WIDTH_SUM  = WIDTH_SUM;
        defparam
                sat_sum1.WIDTH_SUM  = WIDTH_SUM;
        defparam
                sat_sum2.WIDTH_SUM  = WIDTH_SUM;
        // D Register
        // ---------------

        d_ff D0 ( .clk_80(clk_80), .rst_80(rst_80), .d_80(a2_in_80), .q_80(AB00_80) );


        defparam
                D0.REG_SIZE = WIDTH_SUM;

endmodule

codes/testbench.sv
// Code your testbench here
// or browse Examples
module tb;
reg clk_80,rst_80;
reg [8:0] A00_80, A01_80, A02_80, A03_80;
reg [7:0] B00_80, B01_80, B02_80, B03_80;
wire [10:0] AB00_80;

mat_mult m (A00_80, A01_80, A02_80, A03_80, B00_80, B01_80, B02_80, B03_80, 
clk_80, rst_80, AB00_80);

initial begin
	clk_80 = 1'b0;
	repeat (1000) clk_80 = #5 ~clk_80;
	//$finish;
end
initial begin
		rst_80 = 1'b1;
		#10
		rst_80 = 1'b0;
end

initial begin
	A00_80 = 0;
	B00_80 =  0;
	A01_80 = 0;
	B01_80 = 0;
	A02_80 = 0;
	B02_80 = 0;
	A03_80 = 0;
	B03_80 = 0;
	#5;
	A00_80 = 10;//X00
	A01_80 = 20;//X01
	A02_80 = 30;//X02
	A03_80 = 40;//X03
	#0;
	B00_80 =  13;//Y00 = 0.1
	B01_80 = 77;//Y10 = 0.6
	B02_80 = 102;//Y20 = 0.8
	B03_80 = 205;//Y20 = -0.4
	#10;
	B00_80 =  26;//Y01 = 0.2
	B01_80 = 166;//Y11 = -0.7
	B02_80 = 90;//Y21 = 0.7
	B03_80 = 38;//Y31 = 0.3
	#10;
	B00_80 =  38;//Y02 = 0.3
	B01_80 = 154;//Y12 = -0.8
	B02_80 = 77;//Y22 = 0.6
	B03_80 = 230;//Y32 = -0.2
	#10;
	B00_80 =  192;//Y03 = -0.5
	B01_80 = 115;//Y13 = 0.9
	B02_80 = 64;//Y23 = 0.5
	B03_80 = 13;//Y33 = 0.1
	#10;
	A00_80 = 50;//X10
	A01_80 = 60;//X11
	A02_80 = 70;//X12
	A03_80 = 80;//X13
	#0;
	B00_80 =  13;//Y00 = 0.1
	B01_80 = 77;//Y10 = 0.6
	B02_80 = 102;//Y20 = 0.8
	B03_80 = 205;//Y20 = -0.4
	#10;
	B00_80 =  26;//Y01 = 0.2
	B01_80 = 166;//Y11 = -0.7
	B02_80 = 90;//Y21 = 0.7
	B03_80 = 38;//Y31 = 0.3
	#10;
	B00_80 =  38;//Y02 = 0.3
	B01_80 = 154;//Y12 = -0.8
	B02_80 = 77;//Y22 = 0.6
	B03_80 = 230;//Y32 = -0.2
	#10;
	B00_80 =  192;//Y03 = -0.5
	B01_80 = 115;//Y13 = 0.9
	B02_80 = 64;//Y23 = 0.5
	B03_80 = 13;//Y33 = 0.1
	#10;
	A00_80 = 90;//X20
	A01_80 = 100;//X21
	A02_80 = 110;//X22
	A03_80 = 120;//X23
	#0;
	B00_80 =  13;//Y00 = 0.1
	B01_80 = 77;//Y10 = 0.6
	B02_80 = 102;//Y20 = 0.8
	B03_80 = 205;//Y20 = -0.4
	#10;
	B00_80 =  26;//Y01 = 0.2
	B01_80 = 166;//Y11 = -0.7
	B02_80 = 90;//Y21 = 0.7
	B03_80 = 38;//Y31 = 0.3
	#10;
	B00_80 =  38;//Y02 = 0.3
	B01_80 = 154;//Y12 = -0.8
	B02_80 = 77;//Y22 = 0.6
	B03_80 = 230;//Y32 = -0.2
	#10;
	B00_80 =  192;//Y03 = -0.5
	B01_80 = 115;//Y13 = 0.9
	B02_80 = 64;//Y23 = 0.5
	B03_80 = 13;//Y33 = 0.1
	#10;
	A00_80 = 130;//X30
	A01_80 = 140;//X31
	A02_80 = 150;//X32
	A03_80 = 160;//X33
	#0;
	B00_80 =  13;//Y00 = 0.1
	B01_80 = 77;//Y10 = 0.6
	B02_80 = 102;//Y20 = 0.8
	B03_80 = 205;//Y20 = -0.4
	#10;
	B00_80 =  26;//Y01 = 0.2
	B01_80 = 166;//Y11 = -0.7
	B02_80 = 90;//Y21 = 0.7
	B03_80 = 38;//Y31 = 0.3
	#10;
	B00_80 =  38;//Y02 = 0.3
	B01_80 = 154;//Y12 = -0.8
	B02_80 = 77;//Y22 = 0.6
	B03_80 = 230;//Y32 = -0.2
	#10;
	B00_80 =  192;//Y03 = -0.5
	B01_80 = 115;//Y13 = 0.9
	B02_80 = 64;//Y23 = 0.5
	B03_80 = 13;//Y33 = 0.1
	#20;
	$finish;

end
  
  initial begin
	$dumpfile("dump.vcd");
	$dumpvars;
	#10000 
	$finish;
end

endmodule

codes/dump.vcd
$date
	Thu Mar 28 17:51:56 2019
$end
$version
	Icarus Verilog
$end
$timescale
	1ps
$end
$scope module tb $end
$var wire 11 ! AB00_80 [10:0] $end
$var reg 9 " A00_80 [8:0] $end
$var reg 9 # A01_80 [8:0] $end
$var reg 9 $ A02_80 [8:0] $end
$var reg 9 % A03_80 [8:0] $end
$var reg 8 & B00_80 [7:0] $end
$var reg 8 ' B01_80 [7:0] $end
$var reg 8 ( B02_80 [7:0] $end
$var reg 8 ) B03_80 [7:0] $end
$var reg 1 * clk_80 $end
$var reg 1 + rst_80 $end
$scope module m $end
$var wire 9 , A00_80 [8:0] $end
$var wire 9 - A01_80 [8:0] $end
$var wire 9 . A02_80 [8:0] $end
$var wire 9 / A03_80 [8:0] $end
$var wire 8 0 B00_80 [7:0] $end
$var wire 8 1 B01_80 [7:0] $end
$var wire 8 2 B02_80 [7:0] $end
$var wire 8 3 B03_80 [7:0] $end
$var wire 1 * clk_80 $end
$var wire 1 + rst_80 $end
$var wire 9 4 product3_rounded_80 [8:0] $end
$var wire 17 5 product3_80 [16:0] $end
$var wire 9 6 product2_rounded_80 [8:0] $end
$var wire 17 7 product2_80 [16:0] $end
$var wire 9 8 product1_rounded_80 [8:0] $end
$var wire 17 9 product1_80 [16:0] $end
$var wire 9 : product0_rounded_80 [8:0] $end
$var wire 17 ; product0_80 [16:0] $end
$var wire 1 < o_flow2_80 $end
$var wire 1 = o_flow1_80 $end
$var wire 1 > o_flow0_80 $end
$var wire 1 ? c_out2_80 $end
$var wire 1 @ c_out1_80 $end
$var wire 1 A c_out0_80 $end
$var wire 11 B adder2_sum_80 [10:0] $end
$var wire 11 C adder1_sum_80 [10:0] $end
$var wire 11 D adder0_sum_80 [10:0] $end
$var wire 11 E a2_in_80 [10:0] $end
$var wire 11 F a1_in_80 [10:0] $end
$var wire 11 G a0_in_80 [10:0] $end
$var wire 11 H AB00_80 [10:0] $end
$var reg 9 I A00_80_corrected [8:0] $end
$var reg 9 J A01_80_corrected [8:0] $end
$var reg 9 K A02_80_corrected [8:0] $end
$var reg 9 L A03_80_corrected [8:0] $end
$var reg 8 M B00_80_corrected [7:0] $end
$var reg 8 N B01_80_corrected [7:0] $end
$var reg 8 O B02_80_corrected [7:0] $end
$var reg 8 P B03_80_corrected [7:0] $end
$scope module D0 $end
$var wire 1 * clk_80 $end
$var wire 1 + rst_80 $end
$var wire 11 Q d_80 [10:0] $end
$var reg 11 R q_80 [10:0] $end
$upscope $end
$scope module a0 $end
$var wire 11 S dataa [10:0] $end
$var wire 11 T datab [10:0] $end
$var reg 1 A cout $end
$var reg 1 > overflow $end
$var reg 11 U result [10:0] $end
$upscope $end
$scope module a1 $end
$var wire 11 V dataa [10:0] $end
$var wire 11 W datab [10:0] $end
$var reg 1 @ cout $end
$var reg 1 = overflow $end
$var reg 11 X result [10:0] $end
$upscope $end
$scope module a2 $end
$var wire 11 Y datab [10:0] $end
$var wire 11 Z dataa [10:0] $end
$var reg 1 ? cout $end
$var reg 1 < overflow $end
$var reg 11 [ result [10:0] $end
$upscope $end
$scope module m0 $end
$var wire 9 \ dataa [8:0] $end
$var wire 8 ] datab [7:0] $end
$var wire 17 ^ result [16:0] $end
$upscope $end
$scope module m1 $end
$var wire 9 _ dataa [8:0] $end
$var wire 8 ` datab [7:0] $end
$var wire 17 a result [16:0] $end
$upscope $end
$scope module m2 $end
$var wire 9 b dataa [8:0] $end
$var wire 8 c datab [7:0] $end
$var wire 17 d result [16:0] $end
$upscope $end
$scope module m3 $end
$var wire 9 e dataa [8:0] $end
$var wire 8 f datab [7:0] $end
$var wire 17 g result [16:0] $end
$upscope $end
$scope module r0 $end
$var wire 17 h prod_80 [16:0] $end
$var reg 9 i prod_rounded_80 [8:0] $end
$upscope $end
$scope module r1 $end
$var wire 17 j prod_80 [16:0] $end
$var reg 9 k prod_rounded_80 [8:0] $end
$upscope $end
$scope module r2 $end
$var wire 17 l prod_80 [16:0] $end
$var reg 9 m prod_rounded_80 [8:0] $end
$upscope $end
$scope module r3 $end
$var wire 17 n prod_80 [16:0] $end
$var reg 9 o prod_rounded_80 [8:0] $end
$upscope $end
$scope module sat_sum0 $end
$var wire 1 A carry_80 $end
$var wire 1 > oflow_80 $end
$var wire 11 p sum_80 [10:0] $end
$var reg 11 q sum_saturated_80 [10:0] $end
$upscope $end
$scope module sat_sum1 $end
$var wire 1 @ carry_80 $end
$var wire 1 = oflow_80 $end
$var wire 11 r sum_80 [10:0] $end
$var reg 11 s sum_saturated_80 [10:0] $end
$upscope $end
$scope module sat_sum2 $end
$var wire 1 ? carry_80 $end
$var wire 1 < oflow_80 $end
$var wire 11 t sum_80 [10:0] $end
$var reg 11 u sum_saturated_80 [10:0] $end
$upscope $end
$upscope $end
$upscope $end
$enddefinitions $end
#0
$dumpvars
b11111111110 u
b11111111110 t
b1111111111 s
b0 r
b1111111111 q
b0 p
b0 o
b0 n
b0 m
b0 l
b0 k
b0 j
b0 i
b0 h
b0 g
b0 f
b0 e
b0 d
b0 c
b0 b
b0 a
b0 `
b0 _
b0 ^
b0 ]
b0 \
b11111111110 [
b1111111111 Z
b1111111111 Y
b0 X
b0 W
b0 V
b0 U
b0 T
b0 S
b0 R
b11111111110 Q
b0 P
b0 O
b0 N
b0 M
b0 L
b0 K
b0 J
b0 I
b0 H
b1111111111 G
b1111111111 F
b11111111110 E
b0 D
b0 C
b11111111110 B
0A
0@
0?
1>
1=
0<
b0 ;
b0 :
b0 9
b0 8
b0 7
b0 6
b0 5
b0 4
b0 3
b0 2
b0 1
b0 0
b0 /
b0 .
b0 -
b0 ,
1+
0*
b0 )
b0 (
b0 '
b0 &
b0 %
b0 $
b0 #
b0 "
b0 !
$end
#5000
b1011000 C
b1011000 X
b1011000 r
b1101 D
b1101 U
b1101 p
b1000000 W
b1000000 4
b1000000 o
b11000 V
b11000 6
b11000 m
b1100 T
b1100 8
b1100 k
b1 S
b1 :
b1 i
b10000000001000 5
b10000000001000 g
b10000000001000 n
b11001101 P
b11001101 f
b101111110100 7
b101111110100 d
b101111110100 l
b1100110 O
b1100110 c
b11000000100 9
b11000000100 a
b11000000100 j
b1001101 N
b1001101 `
b10000010 ;
b10000010 ^
b10000010 h
b1101 M
b1101 ]
b11001101 )
b11001101 3
b1100110 (
b1100110 2
b1001101 '
b1001101 1
b1101 &
b1101 0
b101000 L
b101000 e
b11110 K
b11110 b
b10100 J
b10100 _
b1010 I
b1010 \
b101000 %
b101000 /
b11110 $
b11110 .
b10100 #
b10100 -
b1010 "
b1010 ,
1*
#10000
0*
0+
#15000
b100001 C
b100001 X
b100001 r
b11100 D
b11100 U
b11100 p
b1100 W
b1100 4
b1100 o
b10101 V
b10101 6
b10101 m
b11010 T
b11010 8
b11010 k
b10 S
b10 :
b10 i
b11111111110 !
b11111111110 H
b11111111110 R
b10111110000 5
b10111110000 g
b10111110000 n
b100110 P
b100110 f
b101010001100 7
b101010001100 d
b101010001100 l
b1011010 O
b1011010 c
b110011111000 9
b110011111000 a
b110011111000 j
b10100110 N
b10100110 `
b100000100 ;
b100000100 ^
b100000100 h
b11010 M
b11010 ]
1*
b100110 )
b100110 3
b1011010 (
b1011010 2
b10100110 '
b10100110 1
b11010 &
b11010 0
#20000
0*
#25000
b1011010 C
b1011010 X
b1011010 r
b11011 D
b11011 U
b11011 p
b1001000 W
b1001000 4
b1001000 o
b10010 V
b10010 6
b10010 m
b11000 T
b11000 8
b11000 k
b11 S
b11 :
b11 i
b10001111110000 5
b10001111110000 g
b10001111110000 n
b11100110 P
b11100110 f
b100100000110 7
b100100000110 d
b100100000110 l
b1001101 O
b1001101 c
b110000001000 9
b110000001000 a
b110000001000 j
b10011010 N
b10011010 `
b101111100 ;
b101111100 ^
b101111100 h
b100110 M
b100110 ]
1*
b11100110 )
b11100110 3
b1001101 (
b1001101 2
b10011010 '
b10011010 1
b100110 &
b100110 0
#30000
0*
#35000
b10011 C
b10011 X
b10011 r
b100001 D
b100001 U
b100001 p
b100 W
b100 4
b100 o
b1111 V
b1111 6
b1111 m
b10010 T
b10010 8
b10010 k
b1111 S
b1111 :
b1111 i
b1000001000 5
b1000001000 g
b1000001000 n
b1101 P
b1101 f
b11110000000 7
b11110000000 d
b11110000000 l
b1000000 O
b1000000 c
b100011111100 9
b100011111100 a
b100011111100 j
b1110011 N
b1110011 `
b11110000000 ;
b11110000000 ^
b11110000000 h
b11000000 M
b11000000 ]
1*
b1101 )
b1101 3
b1000000 (
b1000000 2
b1110011 '
b1110011 1
b11000000 &
b11000000 0
#40000
0*
#45000
b10111000 C
b10111000 X
b10111000 r
b101001 D
b101001 U
b101001 p
b10000000 W
b10000000 4
b10000000 o
b111000 V
b111000 6
b111000 m
b100100 T
b100100 8
b100100 k
b101 S
b101 :
b101 i
b11001101 P
b11001101 f
b1100110 O
b1100110 c
b1001101 N
b1001101 `
b1101 M
b1101 ]
b11001101 )
b11001101 3
b1100110 (
b1100110 2
b1001101 '
b1001101 1
b1101 &
b1101 0
b100000000010000 5
b100000000010000 g
b100000000010000 n
b1010000 L
b1010000 e
b1101111100100 7
b1101111100100 d
b1101111100100 l
b1000110 K
b1000110 b
b1001000001100 9
b1001000001100 a
b1001000001100 j
b111100 J
b111100 _
b1010001010 ;
b1010001010 ^
b1010001010 h
b110010 I
b110010 \
1*
b1010000 %
b1010000 /
b1000110 $
b1000110 .
b111100 #
b111100 -
b110010 "
b110010 ,
#50000
0*
#55000
b1001001 C
b1001001 X
b1001001 r
b1011000 D
b1011000 U
b1011000 p
b11000 W
b11000 4
b11000 o
b110001 V
b110001 6
b110001 m
b1001110 T
b1001110 8
b1001110 k
b1010 S
b1010 :
b1010 i
b101111100000 5
b101111100000 g
b101111100000 n
b100110 P
b100110 f
b1100010011100 7
b1100010011100 d
b1100010011100 l
b1011010 O
b1011010 c
b10011011101000 9
b10011011101000 a
b10011011101000 j
b10100110 N
b10100110 `
b10100010100 ;
b10100010100 ^
b10100010100 h
b11010 M
b11010 ]
1*
b100110 )
b100110 3
b1011010 (
b1011010 2
b10100110 '
b10100110 1
b11010 &
b11010 0
#60000
0*
#65000
b10111010 C
b10111010 X
b10111010 r
b1010111 D
b1010111 U
b1010111 p
b10010000 W
b10010000 4
b10010000 o
b101010 V
b101010 6
b101010 m
b1001000 T
b1001000 8
b1001000 k
b1111 S
b1111 :
b1111 i
b100011111100000 5
b100011111100000 g
b100011111100000 n
b11100110 P
b11100110 f
b1010100001110 7
b1010100001110 d
b1010100001110 l
b1001101 O
b1001101 c
b10010000011000 9
b10010000011000 a
b10010000011000 j
b10011010 N
b10011010 `
b11101101100 ;
b11101101100 ^
b11101101100 h
b100110 M
b100110 ]
1*
b11100110 )
b11100110 3
b1001101 (
b1001101 2
b10011010 '
b10011010 1
b100110 &
b100110 0
#70000
0*
#75000
b101011 C
b101011 X
b101011 r
b10000001 D
b10000001 U
b10000001 p
b1000 W
b1000 4
b1000 o
b100011 V
b100011 6
b100011 m
b110110 T
b110110 8
b110110 k
b1001011 S
b1001011 :
b1001011 i
b10000010000 5
b10000010000 g
b10000010000 n
b1101 P
b1101 f
b1000110000000 7
b1000110000000 d
b1000110000000 l
b1000000 O
b1000000 c
b1101011110100 9
b1101011110100 a
b1101011110100 j
b1110011 N
b1110011 `
b10010110000000 ;
b10010110000000 ^
b10010110000000 h
b11000000 M
b11000000 ]
1*
b1101 )
b1101 3
b1000000 (
b1000000 2
b1110011 '
b1110011 1
b11000000 &
b11000000 0
#80000
0*
#85000
b100011000 C
b100011000 X
b100011000 r
b1000101 D
b1000101 U
b1000101 p
b11000000 W
b11000000 4
b11000000 o
b1011000 V
b1011000 6
b1011000 m
b111100 T
b111100 8
b111100 k
b1001 S
b1001 :
b1001 i
b11001101 P
b11001101 f
b1100110 O
b1100110 c
b1001101 N
b1001101 `
b1101 M
b1101 ]
b11001101 )
b11001101 3
b1100110 (
b1100110 2
b1001101 '
b1001101 1
b1101 &
b1101 0
b110000000011000 5
b110000000011000 g
b110000000011000 n
b1111000 L
b1111000 e
b10101111010100 7
b10101111010100 d
b10101111010100 l
b1101110 K
b1101110 b
b1111000010100 9
b1111000010100 a
b1111000010100 j
b1100100 J
b1100100 _
b10010010010 ;
b10010010010 ^
b10010010010 h
b1011010 I
b1011010 \
1*
b1111000 %
b1111000 /
b1101110 $
b1101110 .
b1100100 #
b1100100 -
b1011010 "
b1011010 ,
#90000
0*
#95000
b1110001 C
b1110001 X
b1110001 r
b10010100 D
b10010100 U
b10010100 p
b100100 W
b100100 4
b100100 o
b1001101 V
b1001101 6
b1001101 m
b10000010 T
b10000010 8
b10000010 k
b10010 S
b10010 :
b10010 i
b1000111010000 5
b1000111010000 g
b1000111010000 n
b100110 P
b100110 f
b10011010101100 7
b10011010101100 d
b10011010101100 l
b1011010 O
b1011010 c
b100000011011000 9
b100000011011000 a
b100000011011000 j
b10100110 N
b10100110 `
b100100100100 ;
b100100100100 ^
b100100100100 h
b11010 M
b11010 ]
1*
b100110 )
b100110 3
b1011010 (
b1011010 2
b10100110 '
b10100110 1
b11010 &
b11010 0
#100000
0*
